tls_client/__init__.py
tls_client/__version__.py
tls_client/cffi.py
tls_client/cookies.py
tls_client/exceptions.py
tls_client/response.py
tls_client/sessions.py
tls_client/structures.py
tls_client/dependencies/__init__.py
tls_client/dependencies/tls-client-amd64.so
tls_client/dependencies/tls-client-arm32.so
tls_client/dependencies/tls-client-arm64.dylib
tls_client/dependencies/tls-client-x86.dylib
tls_client/dependencies/tls-client-x86.so
tls_client/dependencies/tls-client.dll
tls_client_updated-0.1.6.dist-info/LICENSE
tls_client_updated-0.1.6.dist-info/METADATA
tls_client_updated-0.1.6.dist-info/WHEEL
tls_client_updated-0.1.6.dist-info/top_level.txt
tls_client_updated-0.1.6.dist-info/RECORD
